semis/pcc.py
semis-0.0.2.dist-info/LICENSE
semis-0.0.2.dist-info/METADATA
semis-0.0.2.dist-info/WHEEL
semis-0.0.2.dist-info/top_level.txt
semis-0.0.2.dist-info/RECORD
