Metadata-Version: 2.1
Name: semis
Version: 0.0.2
Summary: Semi-supervised learning methods
Home-page: https://github.com/caiocarneloz/pycc
Author: Caio Carneloz
Author-email: caiocarneloz@gmail.com
License: MIT License
Keywords: Semi-supervised
Platform: UNKNOWN
Requires-Dist: numpy
